simple_git_infos/__init__.py
simple_git_infos/gitinfos.py
simple_git_infos-0.0.2.dist-info/LICENCE_en
simple_git_infos-0.0.2.dist-info/LICENCE_fr
simple_git_infos-0.0.2.dist-info/METADATA
simple_git_infos-0.0.2.dist-info/WHEEL
simple_git_infos-0.0.2.dist-info/top_level.txt
simple_git_infos-0.0.2.dist-info/RECORD
