Metadata-Version: 2.1
Name: simple-git-infos
Version: 0.0.2
Summary: Simple Git Infos
Author: Marc DEXET
Author-email: marc.dexet@universite-paris-saclay.fr
Classifier: Programming Language :: Python :: 3
Classifier: Operating System :: OS Independent
Classifier: License :: OSI Approved :: CEA CNRS Inria Logiciel Libre License, version 2.1 (CeCILL-2.1)
License-File: LICENCE_en
License-File: LICENCE_fr
Provides-Extra: dev
Requires-Dist: black ; extra == 'dev'
Provides-Extra: inspect
Requires-Dist: typeguard ; extra == 'inspect'
Requires-Dist: coverage ; extra == 'inspect'
Requires-Dist: astroid ; extra == 'inspect'
Provides-Extra: package
Requires-Dist: distlib ; extra == 'package'
Requires-Dist: twine ; extra == 'package'
Provides-Extra: test
Requires-Dist: pytest ; extra == 'test'
